GramAddict/__init__.py
GramAddict/version.py
GramAddict/core/__init__.py
GramAddict/core/decorators.py
GramAddict/core/device_facade.py
GramAddict/core/filter.py
GramAddict/core/interaction.py
GramAddict/core/log.py
GramAddict/core/navigation.py
GramAddict/core/persistent_list.py
GramAddict/core/plugin_loader.py
GramAddict/core/report.py
GramAddict/core/scroll_end_detector.py
GramAddict/core/session_state.py
GramAddict/core/storage.py
GramAddict/core/utils.py
GramAddict/core/views.py
GramAddict/plugins/__init__.py
GramAddict/plugins/action_unfollow_followers.py
GramAddict/plugins/core_arguments.py
GramAddict/plugins/data_analytics.py
GramAddict/plugins/interact_blogger_followers.py
GramAddict/plugins/interact_hashtag_likers.py
GramAddict/plugins/like_from_urls.py
gramaddict_beta-1.2.0.dist-info/LICENSE
gramaddict_beta-1.2.0.dist-info/METADATA
gramaddict_beta-1.2.0.dist-info/WHEEL
gramaddict_beta-1.2.0.dist-info/top_level.txt
gramaddict_beta-1.2.0.dist-info/RECORD
