Metadata-Version: 2.1
Name: gramaddict-beta
Version: 1.2.0
Summary: Completely free and open source human-like Instagram bot. Powered by UIAutomator2 and compatible with basically any android device that can run instagram - real or emulated.
Home-page: https://github.com/GramAddict/bot/
Author: GramAddict Team
Author-email: maintainers@gramaddict.org
License: UNKNOWN
Platform: UNKNOWN
Classifier: Programming Language :: Python :: 3.6
Classifier: Programming Language :: Python :: 3.7
Classifier: Programming Language :: Python :: 3.8
Classifier: Programming Language :: Python :: 3.9
Classifier: Operating System :: OS Independent
Requires-Python: >=3.6
Requires-Dist: colorama (==0.3.7)
Requires-Dist: matplotlib (==3.3.3)
Requires-Dist: uiautomator2 (==2.11.2)
Requires-Dist: numpy (==1.19.3)
